LICENSE
README.md
README.rst
setup.py
spleendata.py
spleendata.egg-info/PKG-INFO
spleendata.egg-info/SOURCES.txt
spleendata.egg-info/dependency_links.txt
spleendata.egg-info/entry_points.txt
spleendata.egg-info/requires.txt
spleendata.egg-info/top_level.txt
tests/test_example.py