Metadata-Version: 2.1
Name: spleendata
Version: 1.0.10
Summary: A ChRIS FS plugin to download a set of spleen data
Home-page: https://github.com/rudolphpienaar/pl-spleendata
Author: FNNDSC
Author-email: dev@babyMRI.org
License: MIT
Classifier: License :: OSI Approved :: MIT License
Classifier: Topic :: Scientific/Engineering
Classifier: Topic :: Scientific/Engineering :: Bio-Informatics
Classifier: Topic :: Scientific/Engineering :: Medical Science Apps.
License-File: LICENSE
Requires-Dist: chris_plugin
Provides-Extra: none
Provides-Extra: dev
Requires-Dist: pytest~=7.1; extra == "dev"
